[
  {
    "name": "Bench Press",
    "primary": ["UPPER_CHEST", "TRICEPS"],
    "secondary": ["FRONT_DELT"],
    "repsCoeff": 10.0,
    "weightCoeff": 1.2,
    "timeCoeff": 0.0
  },
  {
    "name": "Squat",
    "primary": ["QUADRICEPS", "GLUTES"],
    "secondary": ["HAMSTRINGS", "LOWER_BACK"],
    "repsCoeff": 12.0,
    "weightCoeff": 1.0,
    "timeCoeff": 0.0
  },
  {
    "name": "Deadlift",
    "primary": ["LOWER_BACK", "GLUTES", "HAMSTRINGS"],
    "secondary": ["TRAPS", "FOREARMS"],
    "repsCoeff": 15.0,
    "weightCoeff": 1.5,
    "timeCoeff": 0.0
  },
  {
    "name": "Pull-ups",
    "primary": ["LATS", "BICEPS"],
    "secondary": ["UPPER_BACK"],
    "repsCoeff": 20.0,
    "weightCoeff": 0.5,
    "timeCoeff": 0.0
  },
  {
    "name": "Seated Row",
    "primary": ["LATS", "UPPER_BACK"],
    "secondary": ["REAR_DELT"],
    "repsCoeff": 15.0,
    "weightCoeff": 1.0,
    "timeCoeff": 0.0
  },
  {
    "name": "Shoulder Press",
    "primary": ["FRONT_DELT", "MIDDLE_DELT"],
    "secondary": ["TRICEPS"],
    "repsCoeff": 12.0,
    "weightCoeff": 1.0,
    "timeCoeff": 0.0
  },
  {
    "name": "Lateral Raise",
    "primary": ["MIDDLE_DELT"],
    "secondary": [],
    "repsCoeff": 25.0,
    "weightCoeff": 0.3,
    "timeCoeff": 0.0
  },
  {
    "name": "Barbell Curl",
    "primary": ["BICEPS"],
    "secondary": ["FOREARMS"],
    "repsCoeff": 15.0,
    "weightCoeff": 0.8,
    "timeCoeff": 0.0
  },
  {
    "name": "Triceps Dips",
    "primary": ["TRICEPS"],
    "secondary": ["LOWER_CHEST"],
    "repsCoeff": 15.0,
    "weightCoeff": 0.7,
    "timeCoeff": 0.0
  },
  {
    "name": "Leg Press",
    "primary": ["QUADRICEPS"],
    "secondary": ["GLUTES", "HAMSTRINGS"],
    "repsCoeff": 10.0,
    "weightCoeff": 1.2,
    "timeCoeff": 0.0
  },
  {
    "name": "Calf Raise",
    "primary": ["CALVES"],
    "secondary": [],
    "repsCoeff": 20.0,
    "weightCoeff": 0.4,
    "timeCoeff": 0.0
  },
  {
    "name": "Crunches",
    "primary": ["ABDOMINALS"],
    "secondary": ["OBLIQUES"],
    "repsCoeff": 30.0,
    "weightCoeff": 0.0,
    "timeCoeff": 0.5
  },
  {
    "name": "Russian Twists",
    "primary": ["OBLIQUES"],
    "secondary": ["ABDOMINALS"],
    "repsCoeff": 25.0,
    "weightCoeff": 0.0,
    "timeCoeff": 0.7
  },
  {
    "name": "Plank",
    "primary": ["CORE"],
    "secondary": ["LOWER_BACK"],
    "repsCoeff": 0.0,
    "weightCoeff": 0.0,
    "timeCoeff": 2.5
  },
  {
    "name": "Neck Flexion",
    "primary": ["NECK"],
    "secondary": [],
    "repsCoeff": 15.0,
    "weightCoeff": 0.2,
    "timeCoeff": 0.0
  },
  {
    "name": "Hip Thrust",
    "primary": ["GLUTES"],
    "secondary": ["HAMSTRINGS"],
    "repsCoeff": 15.0,
    "weightCoeff": 1.0,
    "timeCoeff": 0.0
  },
  {
    "name": "Face Pulls",
    "primary": ["REAR_DELT", "TRAPS"],
    "secondary": ["ROTATOR_CUFF"],
    "repsCoeff": 20.0,
    "weightCoeff": 0.6,
    "timeCoeff": 0.0
  },
  {
    "name": "Swimming",
    "primary": ["CARDIO"],
    "secondary": ["LATS", "CORE"],
    "repsCoeff": 0.0,
    "weightCoeff": 0.0,
    "timeCoeff": 2.0
  },
  {
    "name": "Adductor Machine",
    "primary": ["ADDUCTORS"],
    "secondary": [],
    "repsCoeff": 15.0,
    "weightCoeff": 0.9,
    "timeCoeff": 0.0
  },
  {
    "name": "Dumbbell Fly",
    "primary": ["UPPER_CHEST"],
    "secondary": ["FRONT_DELT"],
    "repsCoeff": 14.0,
    "weightCoeff": 0.8,
    "timeCoeff": 0.0
  },
  {
    "name": "Kettlebell Swing",
    "primary": ["GLUTES","HAMSTRINGS"],
    "secondary": ["LOWER_BACK"],
    "repsCoeff": 12.0,
    "weightCoeff": 0.9,
    "timeCoeff": 0.0
  },
  {
    "name": "Farmer's Walk",
    "primary": ["FOREARMS","TRAPS"],
    "secondary": ["GLUTES"],
    "repsCoeff": 8.0,
    "weightCoeff": 1.1,
    "timeCoeff": 0.2
  },
  {
    "name": "Bulgarian Split Squat",
    "primary": ["QUADRICEPS","GLUTES"],
    "secondary": ["HAMSTRINGS"],
    "repsCoeff": 15.0,
    "weightCoeff": 1.0,
    "timeCoeff": 0.0
  },
  {
    "name": "Sled Push",
    "primary": ["QUADRICEPS","GLUTES"],
    "secondary": [
      "CARDIO"
    ],
    "repsCoeff": 6.0,
    "weightCoeff": 1.4,
    "timeCoeff": 0.3
  },
  {
    "name": "Wall Sit",
    "primary": ["QUADRICEPS"],
    "secondary": [],
    "repsCoeff": 0.0,
    "weightCoeff": 0.0,
    "timeCoeff": 1.0
  },
  {
    "name": "Face Pull",
    "primary": ["REAR_DELT","TRAPS"],
    "secondary": ["UPPER_BACK"],
    "repsCoeff": 18.0,
    "weightCoeff": 0.5,
    "timeCoeff": 0.0
  },
  {
    "name": "Hip Thrust",
    "primary": ["GLUTES"],
    "secondary": ["HAMSTRINGS"],
    "repsCoeff": 14.0,
    "weightCoeff": 1.2,
    "timeCoeff": 0.0
  },
  {
    "name": "Weighted Plank",
    "primary": ["ABDOMINALS"],
    "secondary": ["LOWER_BACK"],
    "repsCoeff": 0.0,
    "weightCoeff": 0.8,
    "timeCoeff": 0.8
  },
  {
    "name": "Sissy Squat",
    "primary": ["QUADRICEPS"],
    "secondary": [],
    "repsCoeff": 20.0,
    "weightCoeff": 0.5,
    "timeCoeff": 0.0
  },
  {
    "name": "Barbell Row",
    "primary": ["LATS"],
    "secondary": ["LOWER_BACK"],
    "repsCoeff": 10.0,
    "weightCoeff": 1.0,
    "timeCoeff": 0.0
  },
  {
    "name": "Machine Chest Press",
    "primary": ["UPPER_CHEST","FRONT_DELT"],
    "secondary": ["TRICEPS"],
    "repsCoeff": 12.0,
    "weightCoeff": 0.9,
    "timeCoeff": 0.0
  },
  {
    "name": "Skull Crushers",
    "primary": ["TRICEPS"],
    "secondary": [],
    "repsCoeff": 16.0,
    "weightCoeff": 0.8,
    "timeCoeff": 0.0
  },
  {
    "name": "Reverse Curl",
    "primary": ["FOREARMS"],
    "secondary": ["BICEPS"],
    "repsCoeff": 18.0,
    "weightCoeff": 0.6,
    "timeCoeff": 0.0
  },
  {
    "name": "Cable Lateral Raise",
    "primary": ["MIDDLE_DELT"],
    "secondary": [],
    "repsCoeff": 20.0,
    "weightCoeff": 0.4,
    "timeCoeff": 0.0
  },
  {
    "name": "Overhead Tricep Extension",
    "primary": ["TRICEPS"],
    "secondary": [],
    "repsCoeff": 14.0,
    "weightCoeff": 0.7,
    "timeCoeff": 0.0
  },
  {
    "name": "One-arm Dumbbell Row",
    "primary": ["LATS"],
    "secondary": ["UPPER_BACK"],
    "repsCoeff": 15.0,
    "weightCoeff": 1.0,
    "timeCoeff": 0.0
  },
  {
    "name": "Calf Raise",
    "primary": ["CALVES"],
    "secondary": [],
    "repsCoeff": 18.0,
    "weightCoeff": 0.6,
    "timeCoeff": 0.0
  },
  {
    "name": "Battle Ropes",
    "primary": ["CARDIO"],
    "secondary": ["FOREARMS"],
    "repsCoeff": 0.0,
    "weightCoeff": 0.0,
    "timeCoeff": 1.2
  },
  {
    "name": "Hanging Leg Raise",
    "primary": ["ABDOMINALS"],
    "secondary": [],
    "repsCoeff": 16.0,
    "weightCoeff": 0.0,
    "timeCoeff": 0.0
  },
  {
    "name": "T-Bar Row",
    "primary": ["LATS"],
    "secondary": ["LOWER_BACK"],
    "repsCoeff": 10.0,
    "weightCoeff": 1.2,
    "timeCoeff": 0.0
  },
  {
    "name": "Cable Crunch",
    "primary": ["ABDOMINALS"],
    "secondary": [],
    "repsCoeff": 12.0,
    "weightCoeff": 0.5,
    "timeCoeff": 0.0
  },
  {
    "name": "Shrugs",
    "primary": ["TRAPS"],
    "secondary": [],
    "repsCoeff": 20.0,
    "weightCoeff": 1.0,
    "timeCoeff": 0.0
  },
  {
    "name": "Incline Dumbbell Press",
    "primary": ["UPPER_CHEST","FRONT_DELT"],
    "secondary": ["TRICEPS"],
    "repsCoeff": 13.0,
    "weightCoeff": 0.9,
    "timeCoeff": 0.0
  },
  {
    "name": "Cable Pull Through",
    "primary": ["GLUTES","HAMSTRINGS"],
    "secondary": ["LOWER_BACK"],
    "repsCoeff": 12.0,
    "weightCoeff": 0.8,
    "timeCoeff": 0.0
  },
  {
    "name": "Seated Row",
    "primary": ["LATS"],
    "secondary": ["REAR_DELT"],
    "repsCoeff": 14.0,
    "weightCoeff": 0.9,
    "timeCoeff": 0.0
  },
  {
    "name": "Zercher Squat",
    "primary": ["QUADRICEPS","GLUTES"],
    "secondary": ["LOWER_BACK"],
    "repsCoeff": 12.0,
    "weightCoeff": 1.2,
    "timeCoeff": 0.0
  },
  {
    "name": "Chest Dip",
    "primary": ["LOWER_CHEST"],
    "secondary": ["TRICEPS"],
    "repsCoeff": 15.0,
    "weightCoeff": 0.5,
    "timeCoeff": 0.0
  },
  {
    "name": "Medicine Ball Slam",
    "primary": ["CARDIO"],
    "secondary": ["FRONT_DELT"],
    "repsCoeff": 0.0,
    "weightCoeff": 0.0,
    "timeCoeff": 1.0
  },
  {
    "name": "Landmine Press",
    "primary": ["FRONT_DELT","UPPER_CHEST"],
    "secondary": ["TRICEPS"],
    "repsCoeff": 14.0,
    "weightCoeff": 0.7,
    "timeCoeff": 0.0
  },
  {
    "name": "Incline Cable Fly",
    "primary": ["UPPER_CHEST"],
    "secondary": [],
    "repsCoeff": 18.0,
    "weightCoeff": 0.4,
    "timeCoeff": 0.0
  }
]

